README.md
setup.cfg
setup.py
toi
src/__init__.py
src/toi_cli.py
toi.egg-info/PKG-INFO
toi.egg-info/SOURCES.txt
toi.egg-info/dependency_links.txt
toi.egg-info/top_level.txt
toi.egg-info/zip-safe