Metadata-Version: 1.1
Name: toi
Version: 1.0.3
Summary: Converts terraform output to key/vals or json
Home-page: https://github.com/bwagner5/toi
Author: Brandon Wagner
Author-email: brandon@brandonwagner.info
License: MIT
Download-URL: https://github.com/bwagner5/toi/archive/1.0.3.tar.gz
Keywords: Terraform,Packer,HashiCorp
Platform: UNKNOWN
